cdktf_cdktf_provider_newrelic/__init__.py
cdktf_cdktf_provider_newrelic/py.typed
cdktf_cdktf_provider_newrelic/_jsii/__init__.py
cdktf_cdktf_provider_newrelic/_jsii/provider-newrelic@13.11.3.jsii.tgz
cdktf_cdktf_provider_newrelic/account_management/__init__.py
cdktf_cdktf_provider_newrelic/alert_channel/__init__.py
cdktf_cdktf_provider_newrelic/alert_condition/__init__.py
cdktf_cdktf_provider_newrelic/alert_muting_rule/__init__.py
cdktf_cdktf_provider_newrelic/alert_policy/__init__.py
cdktf_cdktf_provider_newrelic/alert_policy_channel/__init__.py
cdktf_cdktf_provider_newrelic/api_access_key/__init__.py
cdktf_cdktf_provider_newrelic/application_settings/__init__.py
cdktf_cdktf_provider_newrelic/browser_application/__init__.py
cdktf_cdktf_provider_newrelic/cloud_aws_govcloud_integrations/__init__.py
cdktf_cdktf_provider_newrelic/cloud_aws_govcloud_link_account/__init__.py
cdktf_cdktf_provider_newrelic/cloud_aws_integrations/__init__.py
cdktf_cdktf_provider_newrelic/cloud_aws_link_account/__init__.py
cdktf_cdktf_provider_newrelic/cloud_azure_integrations/__init__.py
cdktf_cdktf_provider_newrelic/cloud_azure_link_account/__init__.py
cdktf_cdktf_provider_newrelic/cloud_gcp_integrations/__init__.py
cdktf_cdktf_provider_newrelic/cloud_gcp_link_account/__init__.py
cdktf_cdktf_provider_newrelic/cloud_oci_link_account/__init__.py
cdktf_cdktf_provider_newrelic/data_newrelic_account/__init__.py
cdktf_cdktf_provider_newrelic/data_newrelic_alert_channel/__init__.py
cdktf_cdktf_provider_newrelic/data_newrelic_alert_policy/__init__.py
cdktf_cdktf_provider_newrelic/data_newrelic_application/__init__.py
cdktf_cdktf_provider_newrelic/data_newrelic_authentication_domain/__init__.py
cdktf_cdktf_provider_newrelic/data_newrelic_cloud_account/__init__.py
cdktf_cdktf_provider_newrelic/data_newrelic_entity/__init__.py
cdktf_cdktf_provider_newrelic/data_newrelic_group/__init__.py
cdktf_cdktf_provider_newrelic/data_newrelic_key_transaction/__init__.py
cdktf_cdktf_provider_newrelic-13.11.3.dist-info/LICENSE
cdktf_cdktf_provider_newrelic-13.11.3.dist-info/METADATA
cdktf_cdktf_provider_newrelic-13.11.3.dist-info/WHEEL
cdktf_cdktf_provider_newrelic-13.11.3.dist-info/top_level.txt
cdktf_cdktf_provider_newrelic-13.11.3.dist-info/RECORD
